schema_creator/__init__.py
schema_creator/factory.py
schema_creator/table.py
dbis_schema_creator-0.1.0.dist-info/METADATA
dbis_schema_creator-0.1.0.dist-info/WHEEL
dbis_schema_creator-0.1.0.dist-info/top_level.txt
dbis_schema_creator-0.1.0.dist-info/RECORD
