Metadata-Version: 2.1
Name: dbis-schema-creator
Version: 0.1.0
Summary: RWTH Aachen Computer Science i5/dbis assets for Lecture Datenbanken und Informationssysteme
Author-email: Til Mohr <til.mohr@rwth-aachen.de>
Project-URL: Homepage, https://git.rwth-aachen.de/i5/teaching/dbis/dbis-schema-creator
Classifier: Programming Language :: Python :: 3.10
Classifier: Programming Language :: Python :: 3.11
Requires-Python: >=3.10
Requires-Dist: sqlalchemy (>=2.0.0)
Requires-Dist: dbis-er-diagram (>=1.0.1)
Requires-Dist: typeguard (>=3.0.0)
